{"object": {"dependencies": [{"basedOn": null, "packageRef": {"identity": "perfect-http", "isLocal": false, "name": "PerfectHTTP", "path": "https://github.com/PerfectlySoft/Perfect-HTTP.git"}, "state": {"checkoutState": {"branch": null, "revision": "1800d923271679170f9beef030566c7290a2d170", "version": "3.0.12"}, "name": "checkout"}, "subpath": "Perfect-HTTP.git--6392294032632002019"}, {"basedOn": null, "packageRef": {"identity": "perfect-libcurl", "isLocal": false, "name": "cURL", "path": "https://github.com/PerfectlySoft/Perfect-libcurl.git"}, "state": {"checkoutState": {"branch": null, "revision": "672f6695d9ae04fce16ad01decef0649e0b872b0", "version": "2.0.6"}, "name": "checkout"}, "subpath": "Perfect-libcurl.git--6269865819486613555"}, {"basedOn": null, "packageRef": {"identity": "perfect-httpserver", "isLocal": false, "name": "PerfectHTTPServer", "path": "https://github.com/PerfectlySoft/Perfect-HTTPServer.git"}, "state": {"checkoutState": {"branch": null, "revision": "53372d8af2cd1b799886576a55e997b27514247d", "version": "3.0.12"}, "name": "checkout"}, "subpath": "Perfect-HTTPServer.git--6671958091389663080"}, {"basedOn": null, "packageRef": {"identity": "perfect-logger", "isLocal": false, "name": "PerfectLogger", "path": "https://github.com/PerfectlySoft/Perfect-Logger.git"}, "state": {"checkoutState": {"branch": null, "revision": "2f1baef51d316d8bc1d919e6d89f55be6b3f914c", "version": "3.0.5"}, "name": "checkout"}, "subpath": "Perfect-Logger.git--429101405906730625"}, {"basedOn": null, "packageRef": {"identity": "storm", "isLocal": false, "name": "StORM", "path": "https://github.com/SwiftORM/StORM.git"}, "state": {"checkoutState": {"branch": null, "revision": "8b0578ef364013e3ce0ee9b83fee73d0d801cd37", "version": "3.2.1"}, "name": "checkout"}, "subpath": "StORM.git-6077292811663054913"}, {"basedOn": null, "packageRef": {"identity": "swiftmoment", "isLocal": false, "name": "SwiftMoment", "path": "https://github.com/iamjono/SwiftMoment.git"}, "state": {"checkoutState": {"branch": null, "revision": "2db870fe30d6ab327458df038a56727f23a3da18", "version": "1.0.0"}, "name": "checkout"}, "subpath": "SwiftMoment.git--2912679366309029826"}, {"basedOn": null, "packageRef": {"identity": "perfect-curl", "isLocal": false, "name": "PerfectCURL", "path": "https://github.com/PerfectlySoft/Perfect-CURL.git"}, "state": {"checkoutState": {"branch": null, "revision": "d81d96a74f43407a4b57a7c5335fd19515b50aeb", "version": "3.0.6"}, "name": "checkout"}, "subpath": "Perfect-CURL.git-8858624468322681619"}, {"basedOn": null, "packageRef": {"identity": "perfect-crud", "isLocal": false, "name": "PerfectCRUD", "path": "https://github.com/PerfectlySoft/Perfect-CRUD.git"}, "state": {"checkoutState": {"branch": null, "revision": "509f1f9849f49743a2cca2656fc7b5858bff9f2f", "version": "1.0.2"}, "name": "checkout"}, "subpath": "Perfect-CRUD.git-7099260549736980491"}, {"basedOn": null, "packageRef": {"identity": "swiftstring", "isLocal": false, "name": "SwiftString", "path": "https://github.com/iamjono/SwiftString.git"}, "state": {"checkoutState": {"branch": null, "revision": "a628671f5d84a31bd9d4220eb434da888f364b79", "version": "2.0.4"}, "name": "checkout"}, "subpath": "SwiftString.git-1364241159374428423"}, {"basedOn": null, "packageRef": {"identity": "perfect-copenssl", "isLocal": false, "name": "COpenSSL", "path": "https://github.com/PerfectlySoft/Perfect-COpenSSL.git"}, "state": {"checkoutState": {"branch": null, "revision": "6a2aafd5e233051deeaba27bdfe8c12d9fa88886", "version": "3.1.3"}, "name": "checkout"}, "subpath": "Perfect-COpenSSL.git--4744624199947727386"}, {"basedOn": null, "packageRef": {"identity": "perfect-thread", "isLocal": false, "name": "PerfectThread", "path": "https://github.com/PerfectlySoft/Perfect-Thread.git"}, "state": {"checkoutState": {"branch": null, "revision": "d783048201086dc2cdc08627041e5001157db7f3", "version": "3.0.4"}, "name": "checkout"}, "subpath": "Perfect-Thread.git-6541237758607105655"}, {"basedOn": null, "packageRef": {"identity": "perfect-requestlogger", "isLocal": false, "name": "PerfectRequestLogger", "path": "https://github.com/PerfectlySoft/Perfect-RequestLogger.git"}, "state": {"checkoutState": {"branch": null, "revision": "c2eaee1f37444b1866ef6967c9d6b5627b2307ef", "version": "3.0.2"}, "name": "checkout"}, "subpath": "Perfect-RequestLogger.git-3102495399181047151"}, {"basedOn": null, "packageRef": {"identity": "perfect-crypto", "isLocal": false, "name": "PerfectCrypto", "path": "https://github.com/PerfectlySoft/Perfect-Crypto.git"}, "state": {"checkoutState": {"branch": null, "revision": "18c46956149f9550e1b9540dd84536625284ac29", "version": "3.1.1"}, "name": "checkout"}, "subpath": "Perfect-Crypto.git--5196635702121641122"}, {"basedOn": null, "packageRef": {"identity": "perfect-postgresql", "isLocal": false, "name": "PerfectPostgreSQL", "path": "https://github.com/PerfectlySoft/Perfect-PostgreSQL.git"}, "state": {"checkoutState": {"branch": null, "revision": "9bcbfec4eccadb5f414fd2f3c8727f9dad24ad2f", "version": "3.1.0"}, "name": "checkout"}, "subpath": "Perfect-PostgreSQL.git--5405562302171386633"}, {"basedOn": null, "packageRef": {"identity": "perfect-libpq", "isLocal": false, "name": "libpq", "path": "https://github.com/PerfectlySoft/Perfect-libpq.git"}, "state": {"checkoutState": {"branch": null, "revision": "8b8ff3ceff9af35d9fa4da1f3a93e77dabfcc095", "version": "2.0.1"}, "name": "checkout"}, "subpath": "Perfect-libpq.git--8949598514366864844"}, {"basedOn": null, "packageRef": {"identity": "perfectlib", "isLocal": false, "name": "PerfectLib", "path": "https://github.com/PerfectlySoft/PerfectLib.git"}, "state": {"checkoutState": {"branch": null, "revision": "718432e78c1ce361fe922eea4810130fc72e2191", "version": "3.0.4"}, "name": "checkout"}, "subpath": "PerfectLib.git-3712999737848873669"}, {"basedOn": null, "packageRef": {"identity": "perfect-net", "isLocal": false, "name": "PerfectNet", "path": "https://github.com/PerfectlySoft/Perfect-Net.git"}, "state": {"checkoutState": {"branch": null, "revision": "771e32291e070e22b824c8eb2b37b5ea819f7f97", "version": "3.1.1"}, "name": "checkout"}, "subpath": "Perfect-Net.git-3268755499654502659"}, {"basedOn": null, "packageRef": {"identity": "postgres-storm", "isLocal": false, "name": "PostgresStORM", "path": "https://github.com/SwiftORM/Postgres-StORM.git"}, "state": {"checkoutState": {"branch": null, "revision": "002c045b21a4719d97269cdb6f3c6d4ee2d39901", "version": "3.1.0"}, "name": "checkout"}, "subpath": "Postgres-StORM.git--2456018558473457460"}, {"basedOn": null, "packageRef": {"identity": "perfect-czlib-src", "isLocal": false, "name": "PerfectCZlib", "path": "https://github.com/PerfectlySoft/Perfect-CZlib-src.git"}, "state": {"checkoutState": {"branch": null, "revision": "b63e46909aad937c6434766f8f8c6720d8f3bd05", "version": "0.0.4"}, "name": "checkout"}, "subpath": "Perfect-CZlib-src.git--8503750424862953877"}]}, "version": 2}